pidtune/__init__.py
pidtune/__version__.py
pidtune/models/__init__.py
pidtune/models/controller.py
pidtune/models/plant.py
pidtune/models/plant_alfaro123c.py
pidtune/models/system.py
pidtune/octalib/APC.m
pidtune/octalib/IDFOM.m
pidtune/octalib/f_IDFOM.m
pidtune/octalib/matlab_console
pidtune/octalib/matlab_test.m
pidtune/rules/__init__.py
pidtune/rules/frac_order.py
pidtune/rules/usort.py
pidtune/utils/__init__.py
pidtune/utils/cronePadula2.py
pidtune/utils/identFractOrderModel.py
pidtune/utils/vectUtils.py
pidtune-0.1.0.dist-info/LICENSE
pidtune-0.1.0.dist-info/METADATA
pidtune-0.1.0.dist-info/WHEEL
pidtune-0.1.0.dist-info/top_level.txt
pidtune-0.1.0.dist-info/RECORD
