Metadata-Version: 2.1
Name: pidtune
Version: 0.1.0
Summary: PID tuning server for factorial order models.
Home-page: https://github.com/jeancahu/pidtune
Author: Jeancarlo Hidalgo
Author-email: jeancahu@gmail.com
License: MIT
Classifier: License :: OSI Approved :: MIT License
Classifier: Programming Language :: Python
Classifier: Programming Language :: Python :: 3.8
Classifier: Programming Language :: Python :: Implementation :: CPython
Classifier: Programming Language :: Python :: Implementation :: PyPy
Requires-Python: >=3.8.0
License-File: LICENSE
Requires-Dist: typeguard
Requires-Dist: numpy
Requires-Dist: sympy ==1.5.1
Requires-Dist: pillow
Requires-Dist: control
Requires-Dist: openpyxl
Requires-Dist: pandas
